bleep-0.5.dist-info/METADATA
bleep-0.5.dist-info/WHEEL
bleep-0.5.dist-info/license_files/LICENSE
bleep/bleep.pyi
bleep/data/chars.json
bleep/data/descriptors.json
bleep/data/services.json
bleep/device.py
bleep/gatt/characteristic.py
bleep/gatt/service.py
bleep/gatt/__init__.py
bleep/util.py
bleep/__init__.py
bleep/bleep.pyd
bleep-0.5.dist-info/RECORD
